pylogix/__init__.py
pylogix/adapter.py
pylogix/eip.py
pylogix/lgx_comm.py
pylogix/lgx_device.py
pylogix/lgx_response.py
pylogix/lgx_tag.py
pylogix/lgx_uvendors.py
pylogix/lgx_uvendors.py.bin
pylogix/lgx_vendors.py
pylogix/utils.py
pylogix-1.1.3.dist-info/LICENSE.txt
pylogix-1.1.3.dist-info/METADATA
pylogix-1.1.3.dist-info/WHEEL
pylogix-1.1.3.dist-info/top_level.txt
pylogix-1.1.3.dist-info/RECORD
