Metadata-Version: 2.1
Name: pylogix
Version: 1.1.3
Summary: Read/Write Rockwell Automation Logix based PLC's
Home-page: https://github.com/dmroeder/pylogix
Author: Dustin Roeder
Author-email: dmroeder@gmail.com
License: Apache License 2.0
Classifier: Programming Language :: Python :: 2.7
Classifier: Programming Language :: Python :: 3.6
Classifier: License :: OSI Approved :: Apache Software License
Classifier: Operating System :: OS Independent
License-File: LICENSE.txt
